odoo/addons/sale_order_line_menu/README.rst
odoo/addons/sale_order_line_menu/__init__.py
odoo/addons/sale_order_line_menu/__manifest__.py
odoo/addons/sale_order_line_menu/i18n/es.po
odoo/addons/sale_order_line_menu/i18n/fr.po
odoo/addons/sale_order_line_menu/i18n/fr_BE.po
odoo/addons/sale_order_line_menu/i18n/fr_CA.po
odoo/addons/sale_order_line_menu/i18n/fr_FR.po
odoo/addons/sale_order_line_menu/i18n/it.po
odoo/addons/sale_order_line_menu/i18n/sale_order_line_menu.pot
odoo/addons/sale_order_line_menu/readme/CONTRIBUTORS.rst
odoo/addons/sale_order_line_menu/readme/DESCRIPTION.rst
odoo/addons/sale_order_line_menu/readme/USAGE.rst
odoo/addons/sale_order_line_menu/static/description/icon.png
odoo/addons/sale_order_line_menu/static/description/index.html
odoo/addons/sale_order_line_menu/views/sale_order_line_views.xml
odoo14_addon_sale_order_line_menu-14.0.1.0.1.dev18.dist-info/METADATA
odoo14_addon_sale_order_line_menu-14.0.1.0.1.dev18.dist-info/WHEEL
odoo14_addon_sale_order_line_menu-14.0.1.0.1.dev18.dist-info/top_level.txt
odoo14_addon_sale_order_line_menu-14.0.1.0.1.dev18.dist-info/RECORD
